migra/__init__.py
migra/changes.py
migra/command.py
migra/migra.py
migra/statements.py
migra/util.py
schemahq_migra-1.0.11.dist-info/LICENSE
schemahq_migra-1.0.11.dist-info/WHEEL
schemahq_migra-1.0.11.dist-info/METADATA
schemahq_migra-1.0.11.dist-info/RECORD
