Metadata-Version: 2.1
Name: schemahq-migra
Version: 1.0.11
Summary: Like `diff` but for PostgreSQL schemas
Home-page: https://migra.djrobstep.com/
License: Unlicense
Author: Robert Lechte
Author-email: robertlechte@gmail.com
Classifier: License :: Other/Proprietary License
Classifier: Programming Language :: Python :: 2
Classifier: Programming Language :: Python :: 2.7
Classifier: Programming Language :: Python :: 3
Classifier: Programming Language :: Python :: 3.4
Classifier: Programming Language :: Python :: 3.5
Classifier: Programming Language :: Python :: 3.6
Classifier: Programming Language :: Python :: 3.7
Classifier: Programming Language :: Python :: 3.8
Provides-Extra: pg
Requires-Dist: psycopg2-binary; extra == "pg"
Requires-Dist: schemahq-schemainspect (>=1.0.11,<2.0.0)
Requires-Dist: six
Requires-Dist: sqlbag
Project-URL: Repository, https://github.com/djrobstep/migra
